repoze.sphinx.autointerface-1.0.0-py3.8-nspkg.pth
repoze/sphinx/autointerface.py
repoze/sphinx/tests/__init__.py
repoze/sphinx/tests/test_autointerface.py
repoze/sphinx/tests/util.py
repoze/sphinx/tests/root/conf.py
repoze.sphinx.autointerface-1.0.0.dist-info/LICENSE.txt
repoze.sphinx.autointerface-1.0.0.dist-info/METADATA
repoze.sphinx.autointerface-1.0.0.dist-info/WHEEL
repoze.sphinx.autointerface-1.0.0.dist-info/namespace_packages.txt
repoze.sphinx.autointerface-1.0.0.dist-info/top_level.txt
repoze.sphinx.autointerface-1.0.0.dist-info/RECORD
