Metadata-Version: 2.1
Name: repoze.sphinx.autointerface
Version: 1.0.0
Summary: Sphinx extension: auto-generates API docs from Zope interfaces
Home-page: https://github.com/repoze/repoze.sphinx.autointerface/
Author: Agendaless Consulting
Author-email: repoze-dev@lists.repoze.org
License: BSD-derived (Repoze)
Project-URL: Documentation, https://github.com/repoze/repoze.sphinx.autointerface/
Project-URL: Changelog, https://github.com/repoze/repoze.sphinx.autointerface/blob/master/CHANGES.rst
Project-URL: Issue Tracker, https://github.com/repoze/repoze.sphinx.autointerface/issues
Keywords: web wsgi zope Sphinx
Platform: UNKNOWN
Classifier: Development Status :: 5 - Production/Stable
Classifier: Intended Audience :: Developers
Classifier: Programming Language :: Python :: 3
Classifier: Programming Language :: Python :: 3.6
Classifier: Programming Language :: Python :: 3.7
Classifier: Programming Language :: Python :: 3.8
Classifier: Programming Language :: Python :: 3.9
Classifier: Programming Language :: Python :: 3.10
Classifier: Programming Language :: Python :: Implementation :: CPython
Classifier: Programming Language :: Python :: Implementation :: PyPy
Requires-Python: >=3.6
License-File: LICENSE.txt
Requires-Dist: zope.interface
Requires-Dist: Sphinx (>=4.0)
Requires-Dist: setuptools
Provides-Extra: test
Requires-Dist: zope.testrunner ; extra == 'test'
